Benchmarking/__init__.py
Benchmarking/_configuration/__init__.py
Benchmarking/_configuration/config.py
Benchmarking/_database/__init__.py
Benchmarking/_database/collection.py
Benchmarking/_database/common.py
Benchmarking/_database/models.py
Benchmarking/_templates/__init__.py
Benchmarking/_templates/flame_graph.py
Benchmarking/_templates/heatmap.py
Benchmarking/_utilities/__init__.py
Benchmarking/_utilities/decorators.py
Benchmarking/_utilities/defaults.py
Benchmarking/_utilities/exceptions.py
Benchmarking/profiling/__init__.py
Benchmarking/profiling/instrumentation.py
Benchmarking/profiling/interpreters.py
Benchmarking/profiling/intrusive.py
Benchmarking/profiling/non_intrusive.py
Benchmarking/statistical/__init__.py
Benchmarking/statistical/heuristics.py
Benchmarking/statistical/hypothesis_tests.py
Benchmarking/statistical/measurements.py
Benchmarking/statistical/result_formats.py
Benchmarking/statistical/verification.py
Benchmarking/visualizations/__init__.py
Benchmarking/visualizations/_line_graphs.py
Benchmarking/visualizations/_scatter_plots.py
Benchmarking/visualizations/bar_graphs.py
Benchmarking/visualizations/flame_graphs.py
Benchmarking/visualizations/heat_maps.py
python_benchmark_harness-1.0.3.dist-info/LICENSE.md
python_benchmark_harness-1.0.3.dist-info/METADATA
python_benchmark_harness-1.0.3.dist-info/WHEEL
python_benchmark_harness-1.0.3.dist-info/top_level.txt
python_benchmark_harness-1.0.3.dist-info/RECORD
