Metadata-Version: 2.1
Name: python-benchmark-harness
Version: 1.0.3
Summary: A micro/macro benchmark framework for the Python programming language that helps with optimizing your software.
Home-page: https://github.com/JoeyHendricks/python-benchmarks
Author: Joey Hendricks
Author-email: joey.hendricks20@icloud.com
License: MIT
Platform: UNKNOWN
License-File: LICENSE.md
Requires-Dist: SQLAlchemy
Requires-Dist: SQLAlchemy-Utils
Requires-Dist: setuptools
Requires-Dist: numpy
Requires-Dist: pandas
Requires-Dist: Jinja2
Requires-Dist: scipy
Requires-Dist: PyYAML
Requires-Dist: plotly
